_fse.so
python_fse-0.3.3.dist-info/top_level.txt
python_fse-0.3.3.dist-info/RECORD
python_fse-0.3.3.dist-info/METADATA
python_fse-0.3.3.dist-info/WHEEL
fse/lib.py
fse/__init__.py
fse/build.py
